nvidia/__init__.py
nvidia/nvml_dev/__init__.py
nvidia/nvml_dev/include/__init__.py
nvidia/nvml_dev/include/nvml.h
nvidia/nvml_dev/lib/x64/nvml.lib
nvidia_nvml_dev_cu11-11.8.86.dist-info/License.txt
nvidia_nvml_dev_cu11-11.8.86.dist-info/METADATA
nvidia_nvml_dev_cu11-11.8.86.dist-info/WHEEL
nvidia_nvml_dev_cu11-11.8.86.dist-info/top_level.txt
nvidia_nvml_dev_cu11-11.8.86.dist-info/RECORD
